abuseipdb_wrapper/__init__.py
abuseipdb_wrapper/__main__.py
abuseipdb_wrapper/__version__.py
abuseipdb_wrapper/abuseipdb_wrapper.py
abuseipdb_wrapper/exports.py
abuseipdb_wrapper/logger.py
abuseipdb_wrapper/tor_enrich.py
abuseipdb_wrapper/utils.py
abuseipdb_wrapper-0.2.0.dist-info/LICENSE
abuseipdb_wrapper-0.2.0.dist-info/METADATA
abuseipdb_wrapper-0.2.0.dist-info/WHEEL
abuseipdb_wrapper-0.2.0.dist-info/entry_points.txt
abuseipdb_wrapper-0.2.0.dist-info/top_level.txt
abuseipdb_wrapper-0.2.0.dist-info/RECORD
