Metadata-Version: 2.1
Name: abuseipdb-wrapper
Version: 0.2.0
Summary: python wrapper for abuseipdb API
Home-page: https://github.com/streanger/abuseipdb-wrapper
Author: streanger
Author-email: divisionexe@gmail.com
License: MIT
Keywords: abuseipdb abuse
Platform: UNKNOWN
Classifier: Programming Language :: Python :: 3
Classifier: License :: OSI Approved :: MIT License
Classifier: Operating System :: OS Independent
Requires-Python: >=3.8
License-File: LICENSE
Requires-Dist: keyring >=24.3.1
Requires-Dist: openpyxl >=3.1.2
Requires-Dist: pwinput >=1.0.3
Requires-Dist: requests >=2.31.0
Requires-Dist: rich >=13.7.1
Requires-Dist: tabulate >=0.9.0
